src/Algotrader.py
src/Broker.py
src/Constants.py
src/DataSource.py
src/FileOps.py
src/Storage.py
src/__init__.py
silicon-0.32.0.dist-info/LICENSE
silicon-0.32.0.dist-info/METADATA
silicon-0.32.0.dist-info/WHEEL
silicon-0.32.0.dist-info/top_level.txt
silicon-0.32.0.dist-info/RECORD
