Metadata-Version: 2.1
Name: silicon
Version: 0.32.0
Summary: An algorithmic trading platform
Home-page: https://github.com/suchak1/hyperdrive
Author: Krish Suchak
Author-email: suchak.krish@gmail.com
License: UNKNOWN
Project-URL: Bug Reports, https://github.com/suchak1/hyperdrive/issues
Project-URL: Source, https://github.com/suchak1/hyperdrive
Platform: UNKNOWN
Requires-Python: >=3.7
Requires-Dist: python-dotenv (==0.15.0)
Requires-Dist: pandas (==1.1.4)
Requires-Dist: robin-stocks (==1.5.2)
Requires-Dist: boto3 (==1.16.9)
Requires-Dist: polygon-api-client (==0.1.8)
Requires-Dist: pytz (==2020.1)
